{
    "attachment_folder": "_v_attachments",
    "created_time": "2018-12-15T23:48:56Z",
    "files": [
    ],
    "image_folder": "",
    "recycle_bin_folder": "_v_recycle_bin",
    "sub_directories": [
        {
            "name": "PHP编程相关"
        },
        {
            "name": "面向对象设计"
        },
        {
            "name": "方法和效率"
        },
        {
            "name": "资源"
        },
        {
            "name": "Nginx"
        },
        {
            "name": "Mysql"
        },
        {
            "name": "Linux"
        },
        {
            "name": "Docker"
        },
        {
            "name": "JavaScript"
        }
    ],
    "tags": [
    ],
    "version": "1"
}
